Metadata-Version: 2.1
Name: mknotebooks
Version: 0.7.1
Summary: Plugin for mkdocs to generate markdown documents from jupyter notebooks.
Home-page: https://github.com/greenape/mknotebooks
Author: Jonathan Gray
Author-email: jonathan.gray@nanosheep.net
License: MIT
Keywords: mkdocs documentation markdown
Platform: MacOS X
Platform: Linux
Classifier: Development Status :: 3 - Alpha
Classifier: Intended Audience :: Developers
Classifier: License :: OSI Approved :: MIT License
Classifier: Programming Language :: Python :: 3.6
Classifier: Programming Language :: Python :: 3.7
Classifier: Programming Language :: Python :: 3.8
Classifier: Natural Language :: English
Classifier: Operating System :: MacOS :: MacOS X
Classifier: Operating System :: POSIX
Classifier: Operating System :: POSIX :: Linux
License-File: LICENSE
Requires-Dist: nbconvert (>=6.0.0)
Requires-Dist: mkdocs (>=1.1)
Requires-Dist: markdown (>=3.3.3)
Requires-Dist: jupyter-client
Requires-Dist: gitpython
